setup.py
torquery/__init__.py
torquery/query.py
torquery/socks.py
torquery.egg-info/PKG-INFO
torquery.egg-info/SOURCES.txt
torquery.egg-info/dependency_links.txt
torquery.egg-info/requires.txt
torquery.egg-info/top_level.txt