Metadata-Version: 1.0
Name: torquery
Version: 0.3
Summary: TOR HTTP queries handler
Home-page: https://github.com/koalalorenzo/torquery
Author: Lorenzo Setale ( http://who.is.lorenzo.setale.me/? )
Author-email: koalalorenzo@gmail.com
License: UNKNOWN
Platform: UNKNOWN
